{
  "tipoRadio01": "si",
  "tipoRadio02": "si",
  "tipoRadio03": "si",
  "tipoRadio04": "si",
  "tipoRadio05": "si",
  "tipoRadio06": "si",
  "tipoRadio07": "si",
  "tipoRadio08": "si",
  "tipoRadio09": "si",
  "tipoRadio10": "si",
  "tipoRadio11": "si",
  "tipoRadio12": "si",
  "tipoRadio13": "si",
  "tipoRadio14": "si",
  "tipoRadio15": "si",
  "tipoRadio16": "si",
  "tipoRadio17": "si",
  "tipoRadio18": "si",
  "tipoRadio19": "si",
  "tipoRadio20": "si",
  "tipoRadio21": "si",
  "tipoRadio22": "si",
  "tipoRadio23": "si",
  "tipoRadio24": "si",
  "tipoRadio25": "si",
  "tipoRadio26": "si",
  "tipoRadio27": "si",
  "tipoRadio28": "si",
  "tipoRadio29": "si",
  "tipoRadio30": "si",
  "tipoRadio31": "si",
  "tipoRadio32": "si",
  "tipoRadio33": "si",
  "tipoRadio34": "si",
  "sectorProductivo": "1",
  "servicio": "1",
  "domicilio": "ficcion",
  "biomestre": "1",
  "numeroEmpleados": "ficcion",
  "domicillio": "ficcion",
  "file1": "ficcion",
  "file2": "ficcion",
  "actualmente": "ficcion",
  "actualmente2": "ficcion",
  "sistemaIdentificacion": "ficcion",
  "lugarRadicacion": "ficcion",
  "sistemaControlInventarios": true,
  "rfcTercero": "ficcion",
  "rfc": "ficcion",
  "nombre": "ficcion",
  "apellidoPaterno": "ficcion",
  "apellidoMaterno": "ficcion",
  "telefono": "ficcion",
  "correoElectronico": "ficcion",
  "monto": "ficcion",
  "operacionesBancarias": "ficcion",
  "llavePago": "ficcion",
  "modalidad": "ficcion",
  "fechaRegistro": "ficcion",
  "numeroAutorizacion": "ficcion",
  "radioAutorizo": "si_autorizo",
  "radioClasificacion": "publica",
  "caracter": "ficcion",
  "nacionalidad": "ficcion",
  "fechaInicio": "2023-10-01",
  "fechaPago": "2023-10-01",
  "entidadFederativa": "ficcion",
  "municipio": "ficcion",
  "tipoDeInstalacion": "ficcion",
  "registroSESAT": "ficcion",
  "descripcion": "ficcion",
  "codigoPostal": "135617"
}
