[
    {
        "clasificaionProductos": "1",
        "especificarProducto": "1",
        "nombreProductoEspecifico": "QA",
        "distintiva": "QA",
        "cientifico": "QA",
        "tipoProducto": "1",
        "farmaceutica": "1",
        "fisico": "1",
        "fraccionArancelaria": "04059001",
        "descripcionFraccionArancelaria": "Grasa butirica deshidratada.",
        "cantidadUMT": "1",
        "umt": "Kilogramo",
        "cantidadUMC": "12.00",
        "umc": "1",
        "presentacionFarmaceutica": "CAJA",
        "registroSanitario": "123456",
        "fechaCaducidad": "30/06/2025",
        "paisDeOrigen": "ANGUIA, ANTARTIDA",
        "paisDeProcedencia": "ANGUILA, AUSTRIA",
        "usoEspecifico": "Donaciones, Envasad..."
    }
]