{
  "pais": [
    {
      "id": 1,
      "descripcion": "AFGANISTAN (EMIRATO ISLAMICO DE)"
    },
    {
      "id": 2,
      "descripcion": "ALBANIA (REPUBLICA DE)"
    },
    {
      "id": 3,
      "descripcion": "ALEMANIA (REPUBLICA FEDERAL DE)"
    },
    {
      "id": 4,
      "descripcion": "ANDORRA (PRINCIPADO DE)"
    },
    {
      "id": 5,
      "descripcion": "ANGOLA (REPUBLICA DE)"
    },
    {
      "id": 6,
      "descripcion": "ANGUILA"
    },
    {
      "id": 7,
      "descripcion": "ANTARTIDA"
    },
    {
      "id": 8,
      "descripcion": "ANTIGUA Y BARBUDA (COMUNIDAD BRITANICA DE NACIONES)"
    }
  ],
  "municipio": [
    {
      "id": 1,
      "descripcion": "AGUASCALIENTES"
    },
    {
      "id": 2,
      "descripcion": "ASIENTOS"
    },
    {
      "id": 3,
      "descripcion": "CALVILLO"
    },
    {
      "id": 4,
      "descripcion": "COSIO"
    },
    {
      "id": 5,
      "descripcion": "EL LLANO"
    },
    {
      "id": 6,
      "descripcion": "JESUS MARIA"
    },
    {
      "id": 7,
      "descripcion": "PABELLON DE ARTEAGA"
    }
  ],
  "localidad": [
    {
      "id": 1,
      "descripcion": "ACTOPAN"
    },
    {
      "id": 2,
      "descripcion": "ARROYO OJOCALIENTILLO"
    },
    {
      "id": 3,
      "descripcion": "ARROYO OJOCALIENTILLO"
    },
    {
      "id": 4,
      "descripcion": "ARROYO OJOCALIENTILLO"
    },
    {
      "id": 5,
      "descripcion": "ARROYO QUITA SUEÑO"
    },
    {
      "id": 6,
      "descripcion": "ARROYO QUITA SUEÑO"
    }
  ],
  "codigo_postal": [
    {
      "id": 1,
      "descripcion": "20800"
    },
    {
      "id": 2,
      "descripcion": "20801"
    },
    {
      "id": 3,
      "descripcion": "20802"
    },
    {
      "id": 4,
      "descripcion": "20803"
    },
    {
      "id": 5,
      "descripcion": "20804"
    },
    {
      "id": 6,
      "descripcion": "20805"
    }
  ],
  "colonia": [
    {
      "id": 1,
      "descripcion": "ADOLFO LOPEZ MATEOS"
    },
    {
      "id": 2,
      "descripcion": "ARROYO DE LOS CABALLOS"
    },
    {
      "id": 3,
      "descripcion": "AZTECA"
    },
    {
      "id": 4,
      "descripcion": "BARRIO DE CHICAGO"
    },
    {
      "id": 5,
      "descripcion": "BARRIO EL JUEGUITO"
    },
    {
      "id": 6,
      "descripcion": "BARRIO EL PUENTE"
    }
  ],
  "estado": [
    {
      "id": 1,
      "descripcion": "AGUASCALIENTES"
    },
    {
      "id": 2,
      "descripcion": "BAJA CALIFORNIA"
    },
    {
      "id": 3,
      "descripcion": "BAJA CALIFORNIA SUR"
    },
    {
      "id": 4,
      "descripcion": "CAMPECHE"
    },
    {
      "id": 5,
      "descripcion": "CHIAPAS"
    },
    {
      "id": 6,
      "descripcion": "CHIHUAHUA"
    },
    {
      "id": 7,
      "descripcion": "CIUDAD DE MÉXICO"
    },
    {
      "id": 8,
      "descripcion": "COAHUILA"
    },
    {
      "id": 9,
      "descripcion": "COLIMA"
    },
    {
      "id": 10,
      "descripcion": "DURANGO"
    },
    {
      "id": 11,
      "descripcion": "GUANAJUATO"
    },
    {
      "id": 12,
      "descripcion": "GUERRERO"
    },
    {
      "id": 13,
      "descripcion": "HIDALGO"
    },
    {
      "id": 14,
      "descripcion": "JALISCO"
    },
    {
      "id": 15,
      "descripcion": "ESTADO DE MÉXICO"
    },
    {
      "id": 16,
      "descripcion": "MICHOACÁN"
    },
    {
      "id": 17,
      "descripcion": "MORELOS"
    },
    {
      "id": 18,
      "descripcion": "NAYARIT"
    },
    {
      "id": 19,
      "descripcion": "NUEVO LEÓN"
    },
    {
      "id": 20,
      "descripcion": "OAXACA"
    },
    {
      "id": 21,
      "descripcion": "PUEBLA"
    },
    {
      "id": 22,
      "descripcion": "QUERÉTARO"
    },
    {
      "id": 23,
      "descripcion": "QUINTANA ROO"
    },
    {
      "id": 24,
      "descripcion": "SAN LUIS POTOSÍ"
    },
    {
      "id": 25,
      "descripcion": "SINALOA"
    },
    {
      "id": 26,
      "descripcion": "SONORA"
    },
    {
      "id": 27,
      "descripcion": "TABASCO"
    },
    {
      "id": 28,
      "descripcion": "TAMAULIPAS"
    },
    {
      "id": 29,
      "descripcion": "TLAXCALA"
    },
    {
      "id": 30,
      "descripcion": "VERACRUZ"
    },
    {
      "id": 31,
      "descripcion": "YUCATÁN"
    },
    {
      "id": 32,
      "descripcion": "ZACATECAS"
    }
  ]
}
