{
    "codigo": "00",
    "error": "",
    "causa": "",
    "mensaje": "Operación exitosa.",
    "datos": [
        {
            "idProgramaAutorizado": null,
            "folioPrograma": "2024-9419,2011-7018",
            "tipoPrograma": "PROSEC-ALTEX",
            "movimientoProgramaSE": null,
            "rfc": null,
            "resolucion": "187660195",
            "unidadAdministrativa": null,
            "fechaInicioVigencia": "2024-07-10",
            "fechaFinVigencia": null,
            "actividadProductiva": null,
            "fechaSuspension": null,
            "modalidad": "PROGRAMA NUEVO PRODUCTOR DIRECTO-ALTEX EXPORTADOR DIRECTO",
            "representacionFederal": null,
            "estatus": "Vigente - Activo",
            "contadorGrid": null,
            "idProgramaCompuesto": "121681,2011-7018"
        }
    ]
}