{
    "documentosOpcionales": [
        {
            "descripcion": "Documento_opcional_01",
            "dpi": "300",
            "id": 11,
            "tam": "10000",
            "cargado": false
        },
        {
            "descripcion": "Documento_opcional_02",
            "dpi": "301",
            "id": 12,
            "tam": "11000",
            "cargado": false
        },
        {
            "descripcion": "Documento_opcional_03",
            "dpi": "302",
            "id": 13,
            "tam": "12000",
            "cargado": false
        },
        {
            "descripcion": "Documento_opcional_04",
            "dpi": "303",
            "id": 14,
            "tam": "13000",
            "cargado": false
        },
        {
            "descripcion": "Documento_opcional_05",
            "dpi": "304",
            "id": 15,
            "tam": "14000",
            "cargado": false
        },
        {
            "descripcion": "Documento_opcional_06",
            "dpi": "305",
            "id": 16,
            "tam": "15000",
            "cargado": false
        },
        {
            "descripcion": "Documento_opcional_07",
            "dpi": "306",
            "id": 17,
            "tam": "16000",
            "cargado": false
        },
        {
            "descripcion": "Documento_opcional_08",
            "dpi": "307",
            "id": 18,
            "tam": "17000",
            "cargado": false
        },
        {
            "descripcion": "Documento_opcional_09",
            "dpi": "308",
            "id": 19,
            "tam": "18000",
            "cargado": false
        },
        {
            "descripcion": "Documento_opcional_10",
            "dpi": "309",
            "id": 20,
            "tam": "19000",
            "cargado": false
        }
    ]
}