{
    "tipoDeEndoso": {
        "radioOptions": [
            {
                "label": "Aumento de monto",
                "value": 1
            },
            {
                "label": "Aumento de monto y renovación/ampliación de vigencia",
                "value": 2
            },
            {
                "label": "Modificación de denominación o razón social",
                "value": 3
            },
            {
                "label": "Renovación/ampliación de vigencia",
                "value": 4
            }
        ],
        "isRequired": true
    },
    "tipoDeGarantia": {
        "radioOptions": [
            {
                "label": "Fianza",
                "value": 1
            },
            {
                "label": "Carta de crédito",
                "value": 2
            }
        ],
        "isRequired": true
    },
    "modalidadDeLaGarantia": {
        "radioOptions": [
            {
                "label": "Garantía revolvente",
                "value": 1
            },
            {
                "label": "Garantía individual",
                "value": 2
            }
        ],
        "isRequired": true
    },
    "tipoSector": {
        "radioOptions": [
            {
                "label": "Sector productivo",
                "value": 1
            },
            {
                "label": "Sector servicio",
                "value": 2
            }
        ],
        "isRequired": true
    },
    "requisitos": {
        "radioOptions": [
            {
                "label": "Si",
                "value": 1
            },
            {
                "label": "No",
                "value": 2
            }
        ],
        "isRequired": true
    }
}